mm_base1/__init__.py
mm_base1/app.py
mm_base1/config.py
mm_base1/db.py
mm_base1/errors.py
mm_base1/jinja.py
mm_base1/json_encoder.py
mm_base1/models.py
mm_base1/py.typed
mm_base1/server.py
mm_base1/telegram.py
mm_base1/utils.py
mm_base1/routers/__init__.py
mm_base1/routers/base_ui_router.py
mm_base1/routers/dconfig_router.py
mm_base1/routers/dlog_router.py
mm_base1/routers/dvalue_router.py
mm_base1/routers/system_router.py
mm_base1/services/__init__.py
mm_base1/services/base.py
mm_base1/services/dconfig_service.py
mm_base1/services/dvalue_service.py
mm_base1/services/system_service.py
mm_base1/static/bootstrap-table-sticky-header.min.css
mm_base1/static/bootstrap-table-sticky-header.min.js
mm_base1/static/bootstrap-table.min.css
mm_base1/static/bootstrap-table.min.js
mm_base1/static/bootstrap.bundle.min.js
mm_base1/static/bootstrap.bundle.min.js.map
mm_base1/static/bootstrap.min.css
mm_base1/static/bootstrap.min.css.map
mm_base1/static/favicon.ico
mm_base1/static/jquery-3.7.0.min.js
mm_base1/static/mm-b1.css
mm_base1/static/sortable.min.css
mm_base1/static/sortable.min.js
mm_base1/templates/dconfig.j2
mm_base1/templates/dlogs.j2
mm_base1/templates/dvalue.j2
mm_base1/templates/login.j2
mm_base1/templates/system.j2
mm_base1/templates/update_dconfig.j2
mm_base1/templates/update_dconfig_multiline.j2
mm_base1/templates/update_dvalue.j2
mm_base1/templates/inc/base.j2
mm_base1/templates/inc/macros/dropdown.j2
mm_base1/templates/inc/macros/inline_form.j2
mm_base1/templates/inc/macros/simple_form.j2
mm_base1/templates/inc/macros/table_form.j2
mm_base1-0.2.2.dist-info/METADATA
mm_base1-0.2.2.dist-info/WHEEL
mm_base1-0.2.2.dist-info/RECORD
